MANIFEST.in
README.txt
setup.py
Products/__init__.py
Products.cooptation.egg-info/PKG-INFO
Products.cooptation.egg-info/SOURCES.txt
Products.cooptation.egg-info/dependency_links.txt
Products.cooptation.egg-info/entry_points.txt
Products.cooptation.egg-info/namespace_packages.txt
Products.cooptation.egg-info/not-zip-safe
Products.cooptation.egg-info/requires.txt
Products.cooptation.egg-info/top_level.txt
Products/cooptation/__init__.py
Products/cooptation/addcooptation.py
Products/cooptation/config.py
Products/cooptation/configure.zcml
Products/cooptation/generatedsubscribers.zcml
Products/cooptation/grok.zcml
Products/cooptation/profiles.zcml
Products/cooptation/refresh.txt
Products/cooptation/setuphandlers.py
Products/cooptation/tool.gif
Products/cooptation/viewlets.py
Products/cooptation/wfsubscribers.py
Products/cooptation/content/Cooptation.py
Products/cooptation/content/__init__.py
Products/cooptation/content/interfaces.py
Products/cooptation/i18n/cooptation-plone-fr.po
Products/cooptation/i18n/generated.pot
Products/cooptation/locales/cooptation.pot
Products/cooptation/locales/plone.pot
Products/cooptation/locales/update.sh
Products/cooptation/locales/en/LC_MESSAGES/cooptation.mo
Products/cooptation/locales/en/LC_MESSAGES/cooptation.po
Products/cooptation/locales/fr/LC_MESSAGES/cooptation.mo
Products/cooptation/locales/fr/LC_MESSAGES/cooptation.po
Products/cooptation/profiles/default/controlpanel.xml
Products/cooptation/profiles/default/cooptation_marker.txt
Products/cooptation/profiles/default/cssregistry.xml
Products/cooptation/profiles/default/factorytool.xml
Products/cooptation/profiles/default/import_steps.xml
Products/cooptation/profiles/default/jsregistry.xml
Products/cooptation/profiles/default/metadata.xml
Products/cooptation/profiles/default/skins.xml
Products/cooptation/profiles/default/toolset.xml
Products/cooptation/profiles/default/types.xml
Products/cooptation/profiles/default/workflows.xml
Products/cooptation/profiles/default/types/Cooptation.xml
Products/cooptation/profiles/default/types/Cooptations.xml
Products/cooptation/profiles/default/workflows/CooptationWorkflow/definition.xml
Products/cooptation/profiles/default/workflows/CooptationsWorkflow/definition.xml
Products/cooptation/skins/cooptation_images/Cooptation.gif
Products/cooptation/skins/cooptation_images/Cooptations.gif
