Metadata-Version: 1.1
Name: Products.cooptation
Version: 1.4.3
Summary: Product to coopt new members for Plone. By Ecreall.
Home-page: https://svn.ecreall.com/public/Products.cooptation
Author: Vincent Fretin and Michael Launay
Author-email: development@ecreall.com
License: GPL
Platform: UNKNOWN
Classifier: Programming Language :: Python
Classifier: Topic :: Software Development :: Libraries :: Python Modules
